eve/__init__.py
eve/eve.py
eve/lookahead.py
eve/optimizers.py
eve/radam.py
eve/ralamb.py
eve_optimizer-0.0.7.dist-info/LICENSE
eve_optimizer-0.0.7.dist-info/METADATA
eve_optimizer-0.0.7.dist-info/WHEEL
eve_optimizer-0.0.7.dist-info/top_level.txt
eve_optimizer-0.0.7.dist-info/RECORD
