Metadata-Version: 2.1
Name: eve-optimizer
Version: 0.0.7
Summary: The EVer Evolving Optimizer
Home-page: https://github.com/iyaja/eve
Author: Ajay Uppili Arasanipalai
Author-email: ajayuppili@gmail.com
License: UNKNOWN
Platform: UNKNOWN
Classifier: Programming Language :: Python :: 3
Classifier: License :: OSI Approved :: MIT License
Classifier: Operating System :: OS Independent
Requires-Python: >=3.6
